buggy/__init__.py
buggy/__main__.py
buggy/_cli.py
buggy/_core.py
buggy-0.0.1.dist-info/WHEEL
buggy-0.0.1.dist-info/METADATA
buggy-0.0.1.dist-info/RECORD
